{
  "name": "Dugtrio",
  "id": 51,
  "genderRatio": 4,
  "tags": [],
  "hatchCounter": 20,
  "baseHappiness": 50,
  "catchRate": 50,
  "expRate": "Medium_Fast",
  "eggGroups": [
    "Field"
  ],
  "forms": {
    "default": {
      "types": [
        "Ground"
      ],
      "ability1": "Sand Veil",
      "ability2": "Arena Trap",
      "hiddenAbility": "Sand Force",
      "eventAbilities": [],
      "evolutions": [],
      "stats": {
        "HP": 35,
        "ATK": 100,
        "DEF": 50,
        "SP_ATK": 50,
        "SP_DEF": 70,
        "SPD": 120
      },
      "height": 0.7,
      "weight": 33.3,
      "evs": [
        {
          "stat": "SPD",
          "value": 2
        }
      ],
      "expDrop": 149,
      "classification": "Mole",
      "isBaseForm": true
    },
    "alola": {
      "types": [
        "Ground",
        "Steel"
      ],
      "ability1": "Sand Veil",
      "ability2": "Tangling Hair",
      "hiddenAbility": "Sand Force",
      "eventAbilities": [],
      "evolutions": [],
      "stats": {
        "HP": 35,
        "ATK": 100,
        "DEF": 60,
        "SP_ATK": 50,
        "SP_DEF": 70,
        "SPD": 110
      },
      "height": 0.7,
      "weight": 66.6,
      "evs": [
        {
          "stat": "ATK",
          "value": 2
        }
      ],
      "expDrop": 149,
      "classification": "Mole",
      "isBaseForm": true
    }
  }
}